lightning_rod/__init__.py
lightning_rod/modules/add_comment.bolt
lightning_rod/modules/advancement.bolt
lightning_rod/modules/api.bolt
lightning_rod/modules/cancel_momentum.bolt
lightning_rod/modules/config.bolt
lightning_rod/modules/effect.bolt
lightning_rod/modules/gamemode.bolt
lightning_rod/modules/kill.bolt
lightning_rod/modules/math.bolt
lightning_rod/modules/raw.bolt
lightning_rod/modules/summon.bolt
lightning_rod/modules/tag.bolt
lightning_rod/modules/time.bolt
lightning_rod/modules/utils.bolt
lightning_rod/modules/xp.bolt
lightning_rod/py.typed
lightning_rod-1.0.0.dist-info/LICENSE
lightning_rod-1.0.0.dist-info/METADATA
lightning_rod-1.0.0.dist-info/WHEEL
lightning_rod-1.0.0.dist-info/RECORD
