Metadata-Version: 2.1
Name: lightning_rod
Version: 1.0.0
Summary: Function library for the Bolt scripting language.
Home-page: https://github.com/reapermc/lightning-rod
License: MIT
Keywords: beet,bolt,minecraft,datapack,minecraft-commands,mcfunction,library,reapermc
Author: ArcticYeti
Author-email: arcticyeti1@gmail.com
Requires-Python: >=3.12,<4.0
Classifier: License :: OSI Approved :: MIT License
Classifier: Programming Language :: Python :: 3
Classifier: Programming Language :: Python :: 3.12
Requires-Dist: beet (>=0.89.1)
Requires-Dist: bolt (>=0.36.0)
Requires-Dist: mecha (>=0.73.0)
Requires-Dist: wicked-expressions (>=1.3.2,<2.0.0)
